fetch.v
module adder_32bit(
	input wire [31:0] A,
	input wire [31:0] B,
	output wire [31:0] O
);
	assign O = A + B;
endmodule

module pc_reg(
	input wire CLK,
	input wire RST,
	input wire [31:0] PC_NEXT,	
	output reg [31:0] PC		//32bit PC	
);
	always @(posedge CLK, posedge RST)begin
		if(RST) begin PC <= 32'b0; end
		else begin
			PC <= PC_NEXT;
		end
	end

endmodule

module instruction_memory(
	input wire [31:0]ADDRESS,		//32bit address
	output wire [31:0] INSTRUCTION	//32bit instruction
);

	reg [31:0] rom[0:63];			//64*32bit memory
	initial begin
		$readmemb("instruction_memory.dat", rom);	//read "instruction_memory.data"
	end

	assign INSTRUCTION = rom[ADDRESS[7:2]];		//ADDRESS: 32'bxxx..x00

endmodule

execution.v
module ALU(
	input wire [31:0] IN1,
	input wire [31:0] IN2,
	input wire [3:0] ALU_OPERATION,

	output reg ZERO,
	output reg [31:0] RESULT
);
	always @(*) begin
		case (ALU_OPERATION)
			4'b0000: RESULT = IN1 & IN2;		//AND
			4'b0001: RESULT = IN1 | IN2;		//OR
			4'b0010: RESULT = IN1 + IN2;		//Load, Store, add
			4'b0011: ;
			4'b0100: ;
			4'b0101: ;
			4'b0110: RESULT = IN1 - IN2;		//Branch, subtract
			4'b0111: ;
	
			4'b1000: ;
			4'b1001: ;	
			4'b1010: ;
			4'b1011: ;
			4'b1100: RESULT = ~(IN1 | IN2);		//NOR
			4'b1101: ;
			4'b1110: ;
			4'b1111: ;
		endcase
		if (!RESULT) ZERO = 1'b1;
		else	ZERO = 1'b0;
	end 
endmodule

module data_memory(
	input wire CLK,
	input wire [31:0] ADDRESS,
	input wire [31:0] WRITE_DATA,
	input wire MEM_WRITE,
	input wire MEM_READ,

	output wire [31:0] READ_DATA
);
	reg [31:0] ram[0:63];
	initial begin
		$readmemh("data_memory.dat", ram);		//read "data_memory.data"
	end

	assign READ_DATA = MEM_READ ? ram[ADDRESS[5:0]] : 32'hx;

	always @(posedge CLK) begin
		if(MEM_WRITE) begin ram[ADDRESS[5:0]] = WRITE_DATA;
								$writememh("data_memory_out.dat",ram);end
	end
endmodule

decode.v
module CU(
	input wire [5:0]INSTRUCTION,

	output wire REGDST,
	output wire JUMP,
	output wire BRANCH,
	output wire MEM_READ,
	output wire MEM_TO_REG,
	output wire [1:0] ALU_OP,
	output wire MEM_WRITE,
	output wire ALU_SRC,
	output wire REG_WRITE
);
	reg [9:0] cu_sig;	
	initial begin
		cu_sig = 10'b0;
	end

	parameter R_type 		= 	6'b000000;
	parameter addi			=	6'b001000;
	parameter load 			= 	6'b100011;
	parameter store			=	6'b101011;
	parameter branch		=	6'b000100;
	parameter jump			=	6'b000010; 

	always @(*) begin
		case (INSTRUCTION)
			R_type: 		cu_sig <= 10'b1000010001;
			addi:			cu_sig <= 10'b000X000011;
			load:		 	cu_sig <= 10'b0001100011;
			store:			cu_sig <= 10'bX000X00110;
			branch:			cu_sig <= 10'bX010X01000;
			jump:			cu_sig <= 10'bX1X0XXX0XX;
		endcase
	end

	assign {REGDST, JUMP, BRANCH, MEM_READ, MEM_TO_REG, ALU_OP, MEM_WRITE, ALU_SRC, REG_WRITE} = cu_sig;

endmodule

module ALU_Control(
	input wire [1:0] ALU_OP,
	input wire [5:0] FUNCT,
	
	output reg [3:0] ALU_OPERATION
);
	always @(*) begin
		if(ALU_OP == 2'b00) ALU_OPERATION = 4'b0010;			//add
		else if(ALU_OP == 2'b01) ALU_OPERATION = 4'b0110;		//subtract
		else if(ALU_OP == 2'b10) begin
			case (FUNCT)
				6'b100000: ALU_OPERATION = 4'b0010;			//add
				6'b100010: ALU_OPERATION = 4'b0110;			//subtract
				6'b100100: ALU_OPERATION = 4'b0000;			//AND
				6'b100101: ALU_OPERATION = 4'b0001;			//OR
				6'b101010: ALU_OPERATION = 5'b0111;			//set-on-less-than
			endcase
		end
	end
endmodule

module register_set(
	input wire CLK,
	input wire [4:0]READ_REGISTER1,
	input wire [4:0]READ_REGISTER2,
	input wire [4:0]WRITE_REGISTER,
	input wire [31:0]WRITE_DATA,
	input wire REG_WRITE,

	output wire [31:0]READ_DATA1,
	output wire [31:0]READ_DATA2
);

	reg [31:0] r[0:31];						//32bit register set 32
	wire [31:0] r0, r1, r2, r3, r4, r5, r6, r7;		//use for waveform
	integer i;

	initial begin
		for(i=0; i<32 ;i=i+1)				//initial: all r[] = 0
			r[i] = 32'b0;
	end	
	
	assign READ_DATA1 = r[READ_REGISTER1];
	assign READ_DATA2 = r[READ_REGISTER2];

	assign {r0, r1, r2, r3} = {r[0], r[1], r[2], r[3]};		//use for waveform
	assign {r4, r5, r6, r7} = {r[4], r[5], r[6], r[7]};		//use for waveform


	always @(posedge CLK) begin
		if(REG_WRITE) r[WRITE_REGISTER] = WRITE_DATA;
	end

endmodule

module sign_extend(
	input wire [15:0]DATA,
	output wire [31:0]DATA_32BIT
);

	wire MSB;
	assign MSB = DATA[15];
	assign DATA_32BIT = {{16{MSB}}, DATA};

endmodule

MIPS.v
`include "fetch.v"
`include "decode.v"
`include "execution.v"

module MIPS_CPU(
	input wire CLK,
	input wire RST
);


//Instruction Fetch//		
	wire [31:0]pc;
	wire [31:0]pc_add4;		
	wire [31:0]instruction;

	adder_32bit u_adder(.A(pc),
						.B(32'd4),
						.O(pc_add4));
	pc_reg u_pc_reg(.CLK(CLK),
					.RST(RST),
					.PC_NEXT(pc_mux2_out),
					.PC(pc)); 
	instruction_memory u_instruction_memory(.ADDRESS(pc),
					.INSTRUCTION(instruction));

//Instruction Decoding//
	wire reg_dst, jump, branch, mem_read, mem_to_reg,mem_write, alu_src, reg_write;
	wire [1:0] alu_op;
	wire [31:0] mem_to_reg_data;
	wire [31:0] read_data1;
	wire [31:0] read_data2;
	wire [4:0] write_register;
	wire [31:0] sign_extend_32bit;
	wire [3:0] alu_operation;

	CU u_CU(.INSTRUCTION(instruction[31:26]),
			.REGDST(reg_dst),
			.JUMP(jump),
			.BRANCH(branch),
			.MEM_READ(mem_read),
			.MEM_TO_REG(mem_to_reg),
			.ALU_OP(alu_op),
			.MEM_WRITE(mem_write),
			.ALU_SRC(alu_src),
			.REG_WRITE(reg_write));

	ALU_Control u_ALU_Control(	.ALU_OP(alu_op),
								.FUNCT(instruction[5:0]),
								.ALU_OPERATION(alu_operation));
	
	assign write_register = reg_dst ? instruction[15:11] : instruction[20:16];


	register_set u_register_set(.CLK(CLK),
								.READ_REGISTER1(instruction[25:21]),
								.READ_REGISTER2(instruction[20:16]),
								.WRITE_REGISTER(write_register),
								.WRITE_DATA(mem_to_reg_data),
								.REG_WRITE(reg_write),
								.READ_DATA1(read_data1),
								.READ_DATA2(read_data2));

	sign_extend u_sign_extend(.DATA(instruction[15:0]), .DATA_32BIT(sign_extend_32bit));

//executrion#1: R-Type, Load, Store//
	wire [31:0] alu_in1;
	wire [31:0] alu_in2;
	wire alu_zero;
	wire [31:0] alu_result;
	wire [31:0]	read_data;

	assign alu_in1 = read_data1;
	assign alu_in2 = alu_src ? sign_extend_32bit : read_data2;

	ALU u_ALU(	.IN1(alu_in1),
				.IN2(alu_in2),
				.ALU_OPERATION(alu_operation),
				.ZERO(alu_zero),
				.RESULT(alu_result));

	data_memory u_data_memory(	.CLK(CLK),
								.ADDRESS(alu_result),
								.WRITE_DATA(read_data2),
								.MEM_WRITE(mem_write),
								.MEM_READ(mem_read),
								.READ_DATA(read_data));

	assign mem_to_reg_data = mem_to_reg ? read_data : alu_result;

//executrion#2: Branch//
	wire [31:0] sign_extend_shift_left2;
	wire [31:0] pc_branch;
	wire [31:0] pc_mux1_out;
	wire pc_src;

	assign sign_extend_shift_left2 = (sign_extend_32bit << 2);
	assign pc_src = branch & alu_zero;
	
	adder_32bit u2_adder(.A(pc_add4),
						.B(sign_extend_shift_left2),
						.O(pc_branch));
	assign pc_mux1_out = pc_src ? pc_branch : pc_add4;

//executrion#3: Jump//
	wire [27:0] instruction_shift_left2;
	wire [31:0] jump_address;
	wire [31:0] pc_mux2_out;

	assign instruction_shift_left2 = instruction[25:0] << 2;
	assign jump_address = {pc_add4[31:28],instruction_shift_left2};	//jump region: 2^28 = 256MB
	assign pc_mux2_out = jump ? jump_address : pc_mux1_out;

endmodule



`timescale 1ns/1ps
module tb;

	reg clk;
	reg rst;

	MIPS_CPU u_MIPS(.CLK(clk), .RST(rst));

	initial begin
		#10
		rst = 1'b1;
		clk = 1'b0;
		#10
		rst = 1'b0;
		forever #10 clk = ~clk;
	end

	initial begin
		$dumpvars;
		#5000
		$dumpflush;
		$finish;
	end
endmodule

dump.vcd
$date
	Fri Sep 06 00:58:11 2024
$end
$version
	Icarus Verilog
$end
$timescale
	1ps
$end
$scope module tb $end
$var reg 1 ! clk $end
$var reg 1 " rst $end
$scope module u_MIPS $end
$var wire 1 ! CLK $end
$var wire 1 " RST $end
$var wire 32 # alu_in1 [31:0] $end
$var wire 1 $ pc_src $end
$var wire 5 % write_register [4:0] $end
$var wire 32 & sign_extend_shift_left2 [31:0] $end
$var wire 32 ' sign_extend_32bit [31:0] $end
$var wire 1 ( reg_write $end
$var wire 1 ) reg_dst $end
$var wire 32 * read_data2 [31:0] $end
$var wire 32 + read_data1 [31:0] $end
$var wire 32 , read_data [31:0] $end
$var wire 32 - pc_mux2_out [31:0] $end
$var wire 32 . pc_mux1_out [31:0] $end
$var wire 32 / pc_branch [31:0] $end
$var wire 32 0 pc_add4 [31:0] $end
$var wire 32 1 pc [31:0] $end
$var wire 1 2 mem_write $end
$var wire 32 3 mem_to_reg_data [31:0] $end
$var wire 1 4 mem_to_reg $end
$var wire 1 5 mem_read $end
$var wire 32 6 jump_address [31:0] $end
$var wire 1 7 jump $end
$var wire 28 8 instruction_shift_left2 [27:0] $end
$var wire 32 9 instruction [31:0] $end
$var wire 1 : branch $end
$var wire 1 ; alu_zero $end
$var wire 1 < alu_src $end
$var wire 32 = alu_result [31:0] $end
$var wire 4 > alu_operation [3:0] $end
$var wire 2 ? alu_op [1:0] $end
$var wire 32 @ alu_in2 [31:0] $end
$scope module u2_adder $end
$var wire 32 A B [31:0] $end
$var wire 32 B O [31:0] $end
$var wire 32 C A [31:0] $end
$upscope $end
$scope module u_ALU $end
$var wire 32 D IN1 [31:0] $end
$var wire 32 E IN2 [31:0] $end
$var wire 4 F ALU_OPERATION [3:0] $end
$var reg 32 G RESULT [31:0] $end
$var reg 1 ; ZERO $end
$upscope $end
$scope module u_ALU_Control $end
$var wire 6 H FUNCT [5:0] $end
$var wire 2 I ALU_OP [1:0] $end
$var reg 4 J ALU_OPERATION [3:0] $end
$upscope $end
$scope module u_CU $end
$var wire 6 K INSTRUCTION [5:0] $end
$var wire 1 ( REG_WRITE $end
$var wire 1 ) REGDST $end
$var wire 1 2 MEM_WRITE $end
$var wire 1 4 MEM_TO_REG $end
$var wire 1 5 MEM_READ $end
$var wire 1 7 JUMP $end
$var wire 1 : BRANCH $end
$var wire 1 < ALU_SRC $end
$var wire 2 L ALU_OP [1:0] $end
$var parameter 6 M R_type $end
$var parameter 6 N addi $end
$var parameter 6 O branch $end
$var parameter 6 P jump $end
$var parameter 6 Q load $end
$var parameter 6 R store $end
$var reg 10 S cu_sig [9:0] $end
$upscope $end
$scope module u_adder $end
$var wire 32 T B [31:0] $end
$var wire 32 U O [31:0] $end
$var wire 32 V A [31:0] $end
$upscope $end
$scope module u_data_memory $end
$var wire 32 W ADDRESS [31:0] $end
$var wire 1 ! CLK $end
$var wire 1 5 MEM_READ $end
$var wire 1 2 MEM_WRITE $end
$var wire 32 X WRITE_DATA [31:0] $end
$var wire 32 Y READ_DATA [31:0] $end
$upscope $end
$scope module u_instruction_memory $end
$var wire 32 Z INSTRUCTION [31:0] $end
$var wire 32 [ ADDRESS [31:0] $end
$upscope $end
$scope module u_pc_reg $end
$var wire 1 ! CLK $end
$var wire 32 \ PC_NEXT [31:0] $end
$var wire 1 " RST $end
$var reg 32 ] PC [31:0] $end
$upscope $end
$scope module u_register_set $end
$var wire 1 ! CLK $end
$var wire 32 ^ READ_DATA1 [31:0] $end
$var wire 32 _ READ_DATA2 [31:0] $end
$var wire 5 ` READ_REGISTER1 [4:0] $end
$var wire 5 a READ_REGISTER2 [4:0] $end
$var wire 1 ( REG_WRITE $end
$var wire 32 b WRITE_DATA [31:0] $end
$var wire 5 c WRITE_REGISTER [4:0] $end
$var wire 32 d r7 [31:0] $end
$var wire 32 e r6 [31:0] $end
$var wire 32 f r5 [31:0] $end
$var wire 32 g r4 [31:0] $end
$var wire 32 h r3 [31:0] $end
$var wire 32 i r2 [31:0] $end
$var wire 32 j r1 [31:0] $end
$var wire 32 k r0 [31:0] $end
$var integer 32 l i [31:0] $end
$upscope $end
$scope module u_sign_extend $end
$var wire 16 m DATA [15:0] $end
$var wire 1 n MSB $end
$var wire 32 o DATA_32BIT [31:0] $end
$upscope $end
$upscope $end
$upscope $end
$enddefinitions $end
$comment Show the parameter values. $end
$dumpall
b101011 R
b100011 Q
b10 P
b100 O
b1000 N
b0 M
$end
#0
$dumpvars
bx o
xn
bx m
b100000 l
b0 k
b0 j
b0 i
b0 h
b0 g
b0 f
b0 e
b0 d
bx c
bx b
bx a
bx `
bx _
bx ^
bx ]
bx \
bx [
bx Z
bx Y
bx X
bx W
bx V
bx U
b100 T
b0 S
b0 L
bx K
b10 J
b0 I
bx H
bx G
b10 F
bx E
bx D
bx C
bx B
bx00 A
bx @
b0 ?
b10 >
bx =
0<
0;
0:
bx 9
bx00 8
07
bx00 6
05
04
bx 3
02
bx 1
bx 0
bx /
bx .
bx -
bx ,
bx +
bx *
0)
0(
bx '
bx00 &
bx %
0$
bx #
x"
x!
$end
#10000
b11001000010100000100100 ,
b11001000010100000100100 Y
15
14
1<
1(
b1100011 S
b11001000010100000100100 3
b11001000010100000100100 b
b10100 /
b10100 B
0;
b100 =
b100 G
b100 W
b1000000000000010000 8
0n
b10000 &
b10000 A
b100 @
b100 E
b1 %
b1 c
b100 '
b100 o
b100 m
b0 *
b0 X
b0 _
b1 a
b0 #
b0 D
b0 +
b0 ^
b0 `
b100 H
b100011 K
b100 -
b100 \
b10001100000000010000000000000100 9
b10001100000000010000000000000100 Z
b1000000000000010000 6
b100 .
b100 0
b100 C
b100 U
b0 1
b0 V
b0 [
b0 ]
0!
1"
#20000
0"
#30000
b0x %
b0x c
x)
05
x4
12
0(
bx000x00110 S
bx 3
bx b
bx ,
bx Y
1;
b0 =
b0 G
b0 W
b1000000000000000000 6
b1000000000000000000 8
b0 &
b0 A
b0 @
b0 E
b0 '
b0 o
b0 m
b0 H
b101011 K
b1000 -
b1000 \
b10101100000000010000000000000000 9
b10101100000000010000000000000000 Z
b1000 .
b1000 /
b1000 B
b1000 0
b1000 C
b1000 U
b100 1
b100 V
b100 [
b100 ]
b11001000010100000100100 j
b11001000010100000100100 *
b11001000010100000100100 X
b11001000010100000100100 _
1!
#40000
0!
#50000
b10 3
b10 b
b10 ,
b10 Y
0)
15
14
02
1(
b1100011 S
0;
b100010 =
b100010 G
b100010 W
b10000000000010001000 6
b10000000000010001000 8
b10001000 &
b10001000 A
b100010 @
b100010 E
b10 %
b10 c
b100010 '
b100010 o
b100010 m
b0 *
b0 X
b0 _
b10 a
b100010 H
b100011 K
b1100 -
b1100 \
b10001100000000100000000000100010 9
b10001100000000100000000000100010 Z
b1100 .
b10010100 /
b10010100 B
b1100 0
b1100 C
b1100 U
b1000 1
b1000 V
b1000 [
b1000 ]
1!
#60000
0!
#70000
b11 3
b11 b
b11 ,
b11 Y
b100011 =
b100011 G
b100011 W
b11000000000010001100 6
b11000000000010001100 8
b10001100 &
b10001100 A
b100011 @
b100011 E
b11 %
b11 c
b100011 '
b100011 o
b100011 m
b11 a
b100011 H
b10000 -
b10000 \
b10001100000000110000000000100011 9
b10001100000000110000000000100011 Z
b10000 .
b10011100 /
b10011100 B
b10000 0
b10000 C
b10000 U
b1100 1
b1100 V
b1100 [
b1100 ]
b10 i
b0 *
b0 X
b0 _
1!
#80000
0!
#90000
b100 %
b100 c
1)
05
04
b10 ?
b10 I
b10 L
0<
b1000010001 S
b101 3
b101 b
bx ,
bx Y
b1000011001000000010000000 6
b1000011001000000010000000 8
b1000000010000000 &
b1000000010000000 A
b11 @
b11 E
b101 =
b101 G
b101 W
b10000000100000 '
b10000000100000 o
b10000000100000 m
b10 #
b10 D
b10 +
b10 ^
b10 `
b100000 H
b0 K
b10100 -
b10100 \
b10000110010000000100000 9
b10000110010000000100000 Z
b10100 .
b1000000010010100 /
b1000000010010100 B
b10100 0
b10100 C
b10100 U
b10000 1
b10000 V
b10000 [
b10000 ]
b11 h
b11 *
b11 X
b11 _
1!
#100000
0!
#110000
x)
x4
b0 ?
b0 I
b0 L
12
1<
0(
bx000x00110 S
bx 3
bx b
b100000000000011000000 6
b100000000000011000000 8
b11000000 &
b11000000 A
b110000 @
b110000 E
b110000 =
b110000 G
b110000 W
b0x00 %
b0x00 c
b110000 '
b110000 o
b110000 m
b101 *
b101 X
b101 _
b100 a
b0 #
b0 D
b0 +
b0 ^
b0 `
b110000 H
b101011 K
b11000 -
b11000 \
b10101100000001000000000000110000 9
b10101100000001000000000000110000 Z
b11000 .
b11011000 /
b11011000 B
b11000 0
b11000 C
b11000 U
b10100 1
b10100 V
b10100 [
b10100 ]
b101 g
1!
#120000
0!
#130000
1$
1;
b110 >
b110 F
b110 J
1:
b1 ?
b1 I
b1 L
02
0<
bx010x01000 S
b100001000000000000001000 6
b100001000000000000001000 8
b1000 &
b1000 A
b11001000010100000100100 @
b11001000010100000100100 E
b0 =
b0 G
b0 W
b0x %
b0x c
b10 '
b10 o
b10 m
b11001000010100000100100 *
b11001000010100000100100 X
b11001000010100000100100 _
b1 a
b11001000010100000100100 #
b11001000010100000100100 D
b11001000010100000100100 +
b11001000010100000100100 ^
b1 `
b10 H
b100 K
b100100 -
b100100 \
b10000001000010000000000000010 9
b10000001000010000000000000010 Z
b100100 .
b100100 /
b100100 B
b11100 0
b11100 C
b11100 U
b11000 1
b11000 V
b11000 [
b11000 ]
1!
#140000
0!
#150000
b101001000010100000100000 3
b101001000010100000100000 b
b1 %
b1 c
b101001000010100000100000 ,
b101001000010100000100000 Y
b10 >
b10 F
b10 J
b101 @
b101 E
0)
0:
15
14
b0 ?
b0 I
b0 L
1<
1(
b1100011 S
0$
b1000000000000010100 6
b1000000000000010100 8
b10100 &
b10100 A
0;
b101 =
b101 G
b101 W
b101 '
b101 o
b101 m
b0 #
b0 D
b0 +
b0 ^
b0 `
b101 H
b100011 K
b101000 -
b101000 \
b10001100000000010000000000000101 9
b10001100000000010000000000000101 Z
b101000 .
b111100 /
b111100 B
b101000 0
b101000 C
b101000 U
b100100 1
b100100 V
b100100 [
b100100 ]
1!
#160000
0!
#170000
b0x %
b0x c
x)
05
x4
12
0(
bx000x00110 S
bx 3
bx b
bx ,
bx Y
b110010 =
b110010 G
b110010 W
b1000000000011001000 6
b1000000000011001000 8
b11001000 &
b11001000 A
b110010 @
b110010 E
b110010 '
b110010 o
b110010 m
b110010 H
b101011 K
b101100 -
b101100 \
b10101100000000010000000000110010 9
b10101100000000010000000000110010 Z
b101100 .
b11110100 /
b11110100 B
b101100 0
b101100 C
b101100 U
b101000 1
b101000 V
b101000 [
b101000 ]
b101001000010100000100000 j
b101001000010100000100000 *
b101001000010100000100000 X
b101001000010100000100000 _
1!
#180000
0!
#190000
17
x:
bx ?
bx I
bx L
02
x<
x(
bx1x0xxx0xx S
bx =
bx G
bx W
b11100 6
b11100 8
b11100 &
b11100 A
b0xxx @
b0xxx E
b0 %
b0 c
b111 '
b111 o
b111 m
b0 *
b0 X
b0 _
b0 a
b111 H
b10 K
b11100 -
b11100 \
b1000000000000000000000000111 9
b1000000000000000000000000111 Z
b110000 .
b1001100 /
b1001100 B
b110000 0
b110000 C
b110000 U
b101100 1
b101100 V
b101100 [
b101100 ]
1!
#200000
0!
#210000
b11001000010100000100100 3
b11001000010100000100100 b
b11001000010100000100100 ,
b11001000010100000100100 Y
b100 =
b100 G
b100 W
0)
07
0:
15
14
b0 ?
b0 I
b0 L
1<
1(
b1100011 S
b100000 -
b100000 \
b1000000000000010000 6
b1000000000000010000 8
b10000 &
b10000 A
b100 @
b100 E
b1 %
b1 c
b100 '
b100 o
b100 m
b101001000010100000100000 *
b101001000010100000100000 X
b101001000010100000100000 _
b1 a
b100 H
b100011 K
b10001100000000010000000000000100 9
b10001100000000010000000000000100 Z
b100000 .
b110000 /
b110000 B
b100000 0
b100000 C
b100000 U
b11100 1
b11100 V
b11100 [
b11100 ]
1!
#220000
0!
#230000
b0x %
b0x c
x)
05
x4
12
0(
bx000x00110 S
bx 3
bx b
bx ,
bx Y
b110001 =
b110001 G
b110001 W
b1000000000011000100 6
b1000000000011000100 8
b11000100 &
b11000100 A
b110001 @
b110001 E
b110001 '
b110001 o
b110001 m
b110001 H
b101011 K
b100100 -
b100100 \
b10101100000000010000000000110001 9
b10101100000000010000000000110001 Z
b100100 .
b11101000 /
b11101000 B
b100100 0
b100100 C
b100100 U
b100000 1
b100000 V
b100000 [
b100000 ]
b11001000010100000100100 j
b11001000010100000100100 *
b11001000010100000100100 X
b11001000010100000100100 _
1!
#240000
0!
#250000
b101001000010100000100000 3
b101001000010100000100000 b
b1 %
b1 c
b101001000010100000100000 ,
b101001000010100000100000 Y
0)
15
14
02
1(
b1100011 S
b101 =
b101 G
b101 W
b1000000000000010100 6
b1000000000000010100 8
b10100 &
b10100 A
b101 @
b101 E
b101 '
b101 o
b101 m
b101 H
b100011 K
b101000 -
b101000 \
b10001100000000010000000000000101 9
b10001100000000010000000000000101 Z
b101000 .
b111100 /
b111100 B
b101000 0
b101000 C
b101000 U
b100100 1
b100100 V
b100100 [
b100100 ]
1!
#260000
0!
#270000
b0x %
b0x c
bx ,
bx Y
bx 3
bx b
x)
05
x4
12
0(
bx000x00110 S
b110010 =
b110010 G
b110010 W
b1000000000011001000 6
b1000000000011001000 8
b11001000 &
b11001000 A
b110010 @
b110010 E
b110010 '
b110010 o
b110010 m
b110010 H
b101011 K
b101100 -
b101100 \
b10101100000000010000000000110010 9
b10101100000000010000000000110010 Z
b101100 .
b11110100 /
b11110100 B
b101100 0
b101100 C
b101100 U
b101000 1
b101000 V
b101000 [
b101000 ]
b101001000010100000100000 j
b101001000010100000100000 *
b101001000010100000100000 X
b101001000010100000100000 _
1!
#280000
0!
#290000
17
x:
bx ?
bx I
bx L
02
x<
x(
bx1x0xxx0xx S
bx =
bx G
bx W
b11100 6
b11100 8
b11100 &
b11100 A
b0xxx @
b0xxx E
b0 %
b0 c
b111 '
b111 o
b111 m
b0 *
b0 X
b0 _
b0 a
b111 H
b10 K
b11100 -
b11100 \
b1000000000000000000000000111 9
b1000000000000000000000000111 Z
b110000 .
b1001100 /
b1001100 B
b110000 0
b110000 C
b110000 U
b101100 1
b101100 V
b101100 [
b101100 ]
1!
#300000
0!
#310000
b11001000010100000100100 3
b11001000010100000100100 b
b11001000010100000100100 ,
b11001000010100000100100 Y
b100 =
b100 G
b100 W
0)
07
0:
15
14
b0 ?
b0 I
b0 L
1<
1(
b1100011 S
b100000 -
b100000 \
b1000000000000010000 6
b1000000000000010000 8
b10000 &
b10000 A
b100 @
b100 E
b1 %
b1 c
b100 '
b100 o
b100 m
b101001000010100000100000 *
b101001000010100000100000 X
b101001000010100000100000 _
b1 a
b100 H
b100011 K
b10001100000000010000000000000100 9
b10001100000000010000000000000100 Z
b100000 .
b110000 /
b110000 B
b100000 0
b100000 C
b100000 U
b11100 1
b11100 V
b11100 [
b11100 ]
1!
#320000
0!
#330000
b0x %
b0x c
bx ,
bx Y
bx 3
bx b
x)
05
x4
12
0(
bx000x00110 S
b110001 =
b110001 G
b110001 W
b1000000000011000100 6
b1000000000011000100 8
b11000100 &
b11000100 A
b110001 @
b110001 E
b110001 '
b110001 o
b110001 m
b110001 H
b101011 K
b100100 -
b100100 \
b10101100000000010000000000110001 9
b10101100000000010000000000110001 Z
b100100 .
b11101000 /
b11101000 B
b100100 0
b100100 C
b100100 U
b100000 1
b100000 V
b100000 [
b100000 ]
b11001000010100000100100 j
b11001000010100000100100 *
b11001000010100000100100 X
b11001000010100000100100 _
1!
#340000
0!
#350000
b101001000010100000100000 3
b101001000010100000100000 b
b1 %
b1 c
b101001000010100000100000 ,
b101001000010100000100000 Y
0)
15
14
02
1(
b1100011 S
b101 =
b101 G
b101 W
b1000000000000010100 6
b1000000000000010100 8
b10100 &
b10100 A
b101 @
b101 E
b101 '
b101 o
b101 m
b101 H
b100011 K
b101000 -
b101000 \
b10001100000000010000000000000101 9
b10001100000000010000000000000101 Z
b101000 .
b111100 /
b111100 B
b101000 0
b101000 C
b101000 U
b100100 1
b100100 V
b100100 [
b100100 ]
1!
#360000
0!
#370000
b0x %
b0x c
bx ,
bx Y
bx 3
bx b
x)
05
x4
12
0(
bx000x00110 S
b110010 =
b110010 G
b110010 W
b1000000000011001000 6
b1000000000011001000 8
b11001000 &
b11001000 A
b110010 @
b110010 E
b110010 '
b110010 o
b110010 m
b110010 H
b101011 K
b101100 -
b101100 \
b10101100000000010000000000110010 9
b10101100000000010000000000110010 Z
b101100 .
b11110100 /
b11110100 B
b101100 0
b101100 C
b101100 U
b101000 1
b101000 V
b101000 [
b101000 ]
b101001000010100000100000 j
b101001000010100000100000 *
b101001000010100000100000 X
b101001000010100000100000 _
1!
#380000
0!
#390000
17
x:
bx ?
bx I
bx L
02
x<
x(
bx1x0xxx0xx S
bx =
bx G
bx W
b11100 6
b11100 8
b11100 &
b11100 A
b0xxx @
b0xxx E
b0 %
b0 c
b111 '
b111 o
b111 m
b0 *
b0 X
b0 _
b0 a
b111 H
b10 K
b11100 -
b11100 \
b1000000000000000000000000111 9
b1000000000000000000000000111 Z
b110000 .
b1001100 /
b1001100 B
b110000 0
b110000 C
b110000 U
b101100 1
b101100 V
b101100 [
b101100 ]
1!
#400000
0!
#410000
b11001000010100000100100 3
b11001000010100000100100 b
b11001000010100000100100 ,
b11001000010100000100100 Y
b100 =
b100 G
b100 W
0)
07
0:
15
14
b0 ?
b0 I
b0 L
1<
1(
b1100011 S
b100000 -
b100000 \
b1000000000000010000 6
b1000000000000010000 8
b10000 &
b10000 A
b100 @
b100 E
b1 %
b1 c
b100 '
b100 o
b100 m
b101001000010100000100000 *
b101001000010100000100000 X
b101001000010100000100000 _
b1 a
b100 H
b100011 K
b10001100000000010000000000000100 9
b10001100000000010000000000000100 Z
b100000 .
b110000 /
b110000 B
b100000 0
b100000 C
b100000 U
b11100 1
b11100 V
b11100 [
b11100 ]
1!
#420000
0!
#430000
b0x %
b0x c
bx ,
bx Y
bx 3
bx b
x)
05
x4
12
0(
bx000x00110 S
b110001 =
b110001 G
b110001 W
b1000000000011000100 6
b1000000000011000100 8
b11000100 &
b11000100 A
b110001 @
b110001 E
b110001 '
b110001 o
b110001 m
b110001 H
b101011 K
b100100 -
b100100 \
b10101100000000010000000000110001 9
b10101100000000010000000000110001 Z
b100100 .
b11101000 /
b11101000 B
b100100 0
b100100 C
b100100 U
b100000 1
b100000 V
b100000 [
b100000 ]
b11001000010100000100100 j
b11001000010100000100100 *
b11001000010100000100100 X
b11001000010100000100100 _
1!
#440000
0!
#450000
b101001000010100000100000 3
b101001000010100000100000 b
b1 %
b1 c
b101001000010100000100000 ,
b101001000010100000100000 Y
0)
15
14
02
1(
b1100011 S
b101 =
b101 G
b101 W
b1000000000000010100 6
b1000000000000010100 8
b10100 &
b10100 A
b101 @
b101 E
b101 '
b101 o
b101 m
b101 H
b100011 K
b101000 -
b101000 \
b10001100000000010000000000000101 9
b10001100000000010000000000000101 Z
b101000 .
b111100 /
b111100 B
b101000 0
b101000 C
b101000 U
b100100 1
b100100 V
b100100 [
b100100 ]
1!
#460000
0!
#470000
b0x %
b0x c
bx ,
bx Y
bx 3
bx b
x)
05
x4
12
0(
bx000x00110 S
b110010 =
b110010 G
b110010 W
b1000000000011001000 6
b1000000000011001000 8
b11001000 &
b11001000 A
b110010 @
b110010 E
b110010 '
b110010 o
b110010 m
b110010 H
b101011 K
b101100 -
b101100 \
b10101100000000010000000000110010 9
b10101100000000010000000000110010 Z
b101100 .
b11110100 /
b11110100 B
b101100 0
b101100 C
b101100 U
b101000 1
b101000 V
b101000 [
b101000 ]
b101001000010100000100000 j
b101001000010100000100000 *
b101001000010100000100000 X
b101001000010100000100000 _
1!
#480000
0!
#490000
17
x:
bx ?
bx I
bx L
02
x<
x(
bx1x0xxx0xx S
bx =
bx G
bx W
b11100 6
b11100 8
b11100 &
b11100 A
b0xxx @
b0xxx E
b0 %
b0 c
b111 '
b111 o
b111 m
b0 *
b0 X
b0 _
b0 a
b111 H
b10 K
b11100 -
b11100 \
b1000000000000000000000000111 9
b1000000000000000000000000111 Z
b110000 .
b1001100 /
b1001100 B
b110000 0
b110000 C
b110000 U
b101100 1
b101100 V
b101100 [
b101100 ]
1!
#500000
0!
#510000
b11001000010100000100100 3
b11001000010100000100100 b
b11001000010100000100100 ,
b11001000010100000100100 Y
b100 =
b100 G
b100 W
0)
07
0:
15
14
b0 ?
b0 I
b0 L
1<
1(
b1100011 S
b100000 -
b100000 \
b1000000000000010000 6
b1000000000000010000 8
b10000 &
b10000 A
b100 @
b100 E
b1 %
b1 c
b100 '
b100 o
b100 m
b101001000010100000100000 *
b101001000010100000100000 X
b101001000010100000100000 _
b1 a
b100 H
b100011 K
b10001100000000010000000000000100 9
b10001100000000010000000000000100 Z
b100000 .
b110000 /
b110000 B
b100000 0
b100000 C
b100000 U
b11100 1
b11100 V
b11100 [
b11100 ]
1!
#520000
0!
